README.md
setup.py
ik/__init__.py
ik/other.py
ik.egg-info/PKG-INFO
ik.egg-info/SOURCES.txt
ik.egg-info/dependency_links.txt
ik.egg-info/not-zip-safe
ik.egg-info/top_level.txt