Metadata-Version: 1.0
Name: ik
Version: 0.1
Summary: iks test package
Home-page: http://google.com
Author: ik
Author-email: pedro@gmail.com
License: MIT
Platform: UNKNOWN
